lekinpy/__init__.py
lekinpy/io.py
lekinpy/job.py
lekinpy/machine.py
lekinpy/schedule.py
lekinpy/system.py
lekinpy/algorithms/__init__.py
lekinpy/algorithms/base.py
lekinpy/algorithms/edd.py
lekinpy/algorithms/fcfs.py
lekinpy/algorithms/spt.py
lekinpy/algorithms/wspt.py
lekinpy-0.1.0.dist-info/licenses/LICENSE
lekinpy-0.1.0.dist-info/METADATA
lekinpy-0.1.0.dist-info/WHEEL
lekinpy-0.1.0.dist-info/top_level.txt
lekinpy-0.1.0.dist-info/RECORD
