Metadata-Version: 2.4
Name: lekinpy
Version: 0.1.0
Summary: A Python library for job shop scheduling compatible with LEKIN and JSON formats.
Author-email: Ruturaj Vasant Tambe <rvt2018@nyu.edu>
License-Expression: MIT
Project-URL: Homepage, https://github.com/Ruturaj-Vasant/Lekin_Python
Keywords: scheduling,job shop,lekin,optimization
Classifier: Programming Language :: Python :: 3
Classifier: Programming Language :: Python :: 3.9
Classifier: Programming Language :: Python :: 3.10
Classifier: Programming Language :: Python :: 3.11
Classifier: Programming Language :: Python :: 3.12
Classifier: Operating System :: OS Independent
Classifier: Topic :: Scientific/Engineering :: Mathematics
Requires-Python: >=3.9
License-File: LICENSE
Requires-Dist: numpy>=1.24
Requires-Dist: pandas>=2.0
Provides-Extra: plot
Requires-Dist: matplotlib>=3.8; extra == "plot"
Dynamic: license-file
